i3pystatuscontrib/elisaroaming/ElisaRoaming.py
i3pystatuscontrib/elisaroaming/__init__.py
i3pystatuscontrib.elisaroaming-0.1.2.dist-info/LICENSE
i3pystatuscontrib.elisaroaming-0.1.2.dist-info/METADATA
i3pystatuscontrib.elisaroaming-0.1.2.dist-info/WHEEL
i3pystatuscontrib.elisaroaming-0.1.2.dist-info/top_level.txt
i3pystatuscontrib.elisaroaming-0.1.2.dist-info/RECORD
