Metadata-Version: 2.1
Name: i3pystatuscontrib.elisaroaming
Version: 0.1.2
Summary: Elisa roaming quota module for i3pystatus
Home-page: https://github.com/Mikkula/i3pystatuscontrib-elisaroaming
Author: Mikkula
Author-email: pypi@mikkula1.org
License: UNKNOWN
Platform: UNKNOWN
Requires-Python: >=3.6
Requires-Dist: requests
